onnxstudio/__init__.py
onnxstudio/version.py
onnxstudio-0.0.0.dist-info/METADATA
onnxstudio-0.0.0.dist-info/WHEEL
onnxstudio-0.0.0.dist-info/top_level.txt
onnxstudio-0.0.0.dist-info/zip-safe
onnxstudio-0.0.0.dist-info/RECORD
